{
  "sections": {
    "BROWSE": {
      "id": "BROWSE",
      "headerLabel": "Navigation Bar",
      "archetype": "single-row",
      "x": 127.19999999999999,
      "y": 22.049999999999997,
      "w": 911.177142857143,
      "h": 66.56,
      "childIds": [
        "SOURCE",
        "BROWSE_BTN",
        "TAG_LIST",
        "SOURCE_INDICATOR",
        "PLAYLIST",
        "SEARCH_BTN",
        "MENU_UTILITY"
      ],
      "widthPercent": 78,
      "complexity": "MEDIUM"
    },
    "MEDIA": {
      "id": "MEDIA",
      "headerLabel": "USB/SD Media Ports",
      "archetype": "stacked-rows",
      "x": 27.599999999999994,
      "y": 110.25,
      "w": 148.79999999999998,
      "h": 204.73333333333335,
      "childIds": [
        "USB_PORT",
        "USB_INDICATOR",
        "USB_STOP",
        "SD_INDICATOR",
        "SD_SLOT"
      ],
      "containerAssignment": {
        "row-usb-top": [
          "USB_PORT",
          "USB_INDICATOR"
        ],
        "row-usb-stop": [
          "USB_STOP"
        ],
        "row-sd": [
          "SD_INDICATOR",
          "SD_SLOT"
        ]
      },
      "widthPercent": 14,
      "complexity": "LOW"
    },
    "DISPLAY": {
      "id": "DISPLAY",
      "headerLabel": "9-inch Touch Display",
      "archetype": "single-column",
      "x": 228,
      "y": 104.37,
      "w": 588.48,
      "h": 311.31200000000007,
      "childIds": [
        "TOUCH_DISPLAY"
      ],
      "widthPercent": 64,
      "complexity": "LOW"
    },
    "SELECTOR": {
      "id": "SELECTOR",
      "headerLabel": "Browse Selector",
      "archetype": "single-column",
      "x": 938.4000000000001,
      "y": 154.35,
      "w": 218.8800000000001,
      "h": 257.9266666666666,
      "childIds": [
        "BACK",
        "TAG_TRACK_REMOVE",
        "ROTARY_SELECTOR"
      ],
      "widthPercent": 22,
      "complexity": "LOW"
    },
    "HOT_CUE": {
      "id": "HOT_CUE",
      "headerLabel": "Performance Pads & Mode Buttons",
      "archetype": "dual-column",
      "x": 0,
      "y": 351.33,
      "w": 918.56,
      "h": 219.99999999999994,
      "childIds": [
        "SLIP",
        "QUANTIZE",
        "TIME_MODE_AUTO_CUE",
        "HOT_CUE_A",
        "HOT_CUE_B",
        "HOT_CUE_C",
        "HOT_CUE_D",
        "HOT_CUE_E",
        "HOT_CUE_F",
        "HOT_CUE_G",
        "HOT_CUE_H"
      ],
      "containerAssignment": {
        "left-column": [
          "SLIP",
          "QUANTIZE",
          "TIME_MODE_AUTO_CUE"
        ],
        "right-column": {
          "pads": {
            "controls": [
              "HOT_CUE_A",
              "HOT_CUE_B",
              "HOT_CUE_C",
              "HOT_CUE_D",
              "HOT_CUE_E",
              "HOT_CUE_F",
              "HOT_CUE_G",
              "HOT_CUE_H"
            ],
            "direction": "row"
          }
        }
      },
      "widthPercent": 52,
      "complexity": "HIGH"
    },
    "JOG_CONTROLS": {
      "id": "JOG_CONTROLS",
      "headerLabel": "Jog Wheel Settings",
      "archetype": "dual-column",
      "x": 837.5999999999999,
      "y": 595.35,
      "w": 313.76,
      "h": 145.93999999999994,
      "childIds": [
        "TRACK_FILTER_EDIT",
        "SHORTCUT",
        "VINYL_SPEED_ADJ",
        "JOG_MODE",
        "VINYL_CDJ_INDICATOR",
        "JOG_ADJUST"
      ],
      "containerAssignment": {
        "left-column": [
          "TRACK_FILTER_EDIT",
          "SHORTCUT",
          "VINYL_SPEED_ADJ"
        ],
        "right-column": [
          "JOG_MODE",
          "VINYL_CDJ_INDICATOR",
          "JOG_ADJUST"
        ]
      },
      "widthPercent": 22,
      "complexity": "MEDIUM"
    },
    "LOOP": {
      "id": "LOOP",
      "headerLabel": "Loop Controls",
      "archetype": "stacked-rows",
      "x": -9.6,
      "y": 592.41,
      "w": 334.9866666666667,
      "h": 130.97699999999998,
      "childIds": [
        "LOOP_IN_CUE",
        "LOOP_OUT",
        "RELOOP_EXIT",
        "FOUR_BEAT_LOOP",
        "EIGHT_BEAT_LOOP"
      ],
      "containerAssignment": {
        "row-1": [
          "LOOP_IN_CUE",
          "LOOP_OUT"
        ],
        "row-2": [
          "RELOOP_EXIT",
          "FOUR_BEAT_LOOP",
          "EIGHT_BEAT_LOOP"
        ]
      },
      "widthPercent": 28,
      "complexity": "MEDIUM"
    },
    "CUE_MEMORY": {
      "id": "CUE_MEMORY",
      "headerLabel": "Cue/Loop Memory Controls",
      "archetype": "grid-NxM",
      "x": 706.8,
      "y": 508.6200000000001,
      "w": 392.60000000000014,
      "h": 127.00799999999992,
      "childIds": [
        "CUE_LOOP_CALL_BACK",
        "CUE_LOOP_CALL_FWD",
        "DELETE",
        "MEMORY"
      ],
      "gridCols": 2,
      "gridRows": 2,
      "widthPercent": 23,
      "complexity": "LOW"
    },
    "SYNC": {
      "id": "SYNC",
      "headerLabel": "Beat Sync Controls",
      "archetype": "single-column",
      "x": 1038,
      "y": 692.37,
      "w": 113.27999999999997,
      "h": 124,
      "childIds": [
        "MASTER",
        "KEY_SYNC",
        "BEAT_SYNC_INST_DOUBLES"
      ],
      "widthPercent": 22,
      "complexity": "LOW"
    },
    "TRANSPORT": {
      "id": "TRANSPORT",
      "headerLabel": "Transport Controls",
      "archetype": "stacked-rows",
      "x": 7.199999999999999,
      "y": 740.88,
      "w": 166.88,
      "h": 675.6836666666667,
      "childIds": [
        "BEAT_JUMP_BACK",
        "BEAT_JUMP_FWD",
        "DIRECTION_LEVER",
        "TRACK_SEARCH_BACK",
        "TRACK_SEARCH_FWD",
        "SEARCH_BACK",
        "SEARCH_FWD",
        "CUE_BTN",
        "PLAY_PAUSE"
      ],
      "containerAssignment": {
        "row-beat-jump": [
          "BEAT_JUMP_BACK",
          "BEAT_JUMP_FWD"
        ],
        "row-direction": [
          "DIRECTION_LEVER"
        ],
        "row-track-search": [
          "TRACK_SEARCH_BACK",
          "TRACK_SEARCH_FWD"
        ],
        "row-search": [
          "SEARCH_BACK",
          "SEARCH_FWD"
        ],
        "row-cue": [
          "CUE_BTN"
        ],
        "row-play": [
          "PLAY_PAUSE"
        ]
      },
      "widthPercent": 15,
      "complexity": "HIGH"
    },
    "JOG_WHEEL": {
      "id": "JOG_WHEEL",
      "headerLabel": "Jog Wheel",
      "archetype": "anchor-layout",
      "x": 202.79999999999998,
      "y": 951.6840000000001,
      "w": 740.3600000000001,
      "h": 296.7248000000001,
      "childIds": [
        "JOG_WHEEL",
        "JOG_DISPLAY"
      ],
      "containerAssignment": {
        "secondary-controls": [
          "JOG_DISPLAY"
        ],
        "anchor-element": [
          "JOG_WHEEL"
        ]
      },
      "heightSplits": {
        "cluster": 0.1,
        "anchor": 0.85,
        "gap": 0.05
      },
      "widthPercent": 54,
      "complexity": "MEDIUM"
    },
    "TEMPO": {
      "id": "TEMPO",
      "headerLabel": "Tempo Controls",
      "archetype": "dual-column",
      "x": 958.8000000000001,
      "y": 857.01,
      "w": 228.44000000000017,
      "h": 514.8053333333335,
      "childIds": [
        "TEMPO_RANGE",
        "MASTER_TEMPO",
        "TEMPO_SLIDER",
        "TEMPO_RESET",
        "TEMPO_RESET_INDICATOR"
      ],
      "containerAssignment": {
        "left-column": {
          "mode-buttons": {
            "controls": [
              "TEMPO_RANGE",
              "MASTER_TEMPO"
            ],
            "direction": "column"
          },
          "reset-controls": {
            "controls": [
              "TEMPO_RESET",
              "TEMPO_RESET_INDICATOR"
            ],
            "direction": "row"
          }
        },
        "right-column": [
          "TEMPO_SLIDER"
        ]
      },
      "widthPercent": 20,
      "complexity": "MEDIUM"
    }
  },
  "controls": {
    "SOURCE": {
      "id": "SOURCE",
      "label": "SOURCE",
      "type": "button",
      "x": 135.2,
      "y": 46.05,
      "w": 102.49142857142859,
      "h": 34.56,
      "sectionId": "BROWSE",
      "labelPosition": "on-button",
      "locked": false,
      "spatialNeighbors": {
        "above": null,
        "below": null,
        "left": null,
        "right": "BROWSE_BTN"
      },
      "functionalGroup": "Navigation",
      "shape": "rectangle",
      "surfaceColor": null,
      "buttonStyle": "flat-key",
      "labelDisplay": "on-button",
      "icon": null,
      "hasLed": false,
      "ledColor": null
    },
    "BROWSE_BTN": {
      "id": "BROWSE_BTN",
      "label": "BROWSE",
      "type": "button",
      "x": 267.3142857142857,
      "y": 46.05,
      "w": 102.49142857142859,
      "h": 34.56,
      "sectionId": "BROWSE",
      "labelPosition": "on-button",
      "locked": false,
      "spatialNeighbors": {
        "above": null,
        "below": null,
        "left": "SOURCE",
        "right": "TAG_LIST"
      },
      "functionalGroup": "Navigation",
      "shape": "rectangle",
      "surfaceColor": null,
      "buttonStyle": "flat-key",
      "labelDisplay": "on-button",
      "icon": null,
      "hasLed": false,
      "ledColor": null
    },
    "TAG_LIST": {
      "id": "TAG_LIST",
      "label": "TAG LIST",
      "type": "button",
      "x": 399.42857142857144,
      "y": 46.05,
      "w": 102.49142857142859,
      "h": 34.56,
      "sectionId": "BROWSE",
      "labelPosition": "on-button",
      "locked": false,
      "spatialNeighbors": {
        "above": null,
        "below": null,
        "left": "BROWSE_BTN",
        "right": "SOURCE_INDICATOR"
      },
      "functionalGroup": "Navigation",
      "shape": "rectangle",
      "surfaceColor": null,
      "buttonStyle": "flat-key",
      "labelDisplay": "on-button",
      "icon": null,
      "hasLed": false,
      "ledColor": null
    },
    "SOURCE_INDICATOR": {
      "id": "SOURCE_INDICATOR",
      "label": "SOURCE indicator",
      "type": "led",
      "x": 531.5428571428572,
      "y": 46.05,
      "w": 102.49142857142859,
      "h": 28,
      "sectionId": "BROWSE",
      "labelPosition": "hidden",
      "locked": false,
      "spatialNeighbors": {
        "above": null,
        "below": null,
        "left": "TAG_LIST",
        "right": "PLAYLIST"
      },
      "functionalGroup": "Navigation",
      "shape": "circle",
      "surfaceColor": null,
      "labelDisplay": "hidden",
      "icon": null,
      "hasLed": true,
      "ledColor": "#22c55e",
      "ledVariant": "dot"
    },
    "PLAYLIST": {
      "id": "PLAYLIST",
      "label": "PLAYLIST",
      "type": "button",
      "x": 663.657142857143,
      "y": 46.05,
      "w": 102.49142857142859,
      "h": 34.56,
      "sectionId": "BROWSE",
      "labelPosition": "on-button",
      "locked": false,
      "spatialNeighbors": {
        "above": null,
        "below": null,
        "left": "SOURCE_INDICATOR",
        "right": "SEARCH_BTN"
      },
      "functionalGroup": "Navigation",
      "shape": "rectangle",
      "surfaceColor": null,
      "buttonStyle": "flat-key",
      "labelDisplay": "on-button",
      "icon": null,
      "hasLed": false,
      "ledColor": null
    },
    "SEARCH_BTN": {
      "id": "SEARCH_BTN",
      "label": "SEARCH",
      "type": "button",
      "x": 795.7714285714287,
      "y": 46.05,
      "w": 102.49142857142859,
      "h": 34.56,
      "sectionId": "BROWSE",
      "labelPosition": "on-button",
      "locked": false,
      "spatialNeighbors": {
        "above": null,
        "below": null,
        "left": "PLAYLIST",
        "right": "MENU_UTILITY"
      },
      "functionalGroup": "Navigation",
      "shape": "rectangle",
      "surfaceColor": null,
      "buttonStyle": "flat-key",
      "labelDisplay": "on-button",
      "icon": null,
      "hasLed": false,
      "ledColor": null
    },
    "MENU_UTILITY": {
      "id": "MENU_UTILITY",
      "label": "MENU/UTILITY",
      "type": "button",
      "x": 927.8857142857145,
      "y": 46.05,
      "w": 102.49142857142859,
      "h": 34.56,
      "sectionId": "BROWSE",
      "labelPosition": "on-button",
      "locked": false,
      "spatialNeighbors": {
        "above": null,
        "below": null,
        "left": "SEARCH_BTN",
        "right": null
      },
      "functionalGroup": "Navigation",
      "shape": "rectangle",
      "surfaceColor": null,
      "buttonStyle": "flat-key",
      "labelDisplay": "on-button",
      "icon": null,
      "hasLed": false,
      "ledColor": null
    },
    "SD_INDICATOR": {
      "id": "SD_INDICATOR",
      "label": "SD memory card indicator",
      "type": "led",
      "x": 35.599999999999994,
      "y": 134.25,
      "w": 51.84,
      "h": 47.06666666666667,
      "sectionId": "MEDIA",
      "labelPosition": "hidden",
      "locked": false,
      "spatialNeighbors": {
        "above": "USB_STOP",
        "below": null,
        "left": null,
        "right": "SD_SLOT"
      },
      "functionalGroup": "Media/Storage",
      "shape": "circle",
      "surfaceColor": null,
      "labelDisplay": "hidden",
      "icon": null,
      "hasLed": true,
      "ledColor": "#f59e0b",
      "ledVariant": "dot"
    },
    "SD_SLOT": {
      "id": "SD_SLOT",
      "label": "SD memory card slot",
      "type": "slot",
      "x": 104.39999999999999,
      "y": 134.25,
      "w": 64,
      "h": 47.06666666666667,
      "sectionId": "MEDIA",
      "labelPosition": "hidden",
      "locked": false,
      "spatialNeighbors": {
        "above": null,
        "below": null,
        "left": "SD_INDICATOR",
        "right": null
      },
      "functionalGroup": "Media/Storage",
      "shape": "rectangle",
      "surfaceColor": null,
      "labelDisplay": "hidden",
      "icon": null,
      "hasLed": false,
      "ledColor": null
    },
    "USB_STOP": {
      "id": "USB_STOP",
      "label": "USB STOP",
      "type": "button",
      "x": 35.599999999999994,
      "y": 197.08333333333334,
      "w": 106.88,
      "h": 47.06666666666667,
      "sectionId": "MEDIA",
      "labelPosition": "above",
      "locked": false,
      "spatialNeighbors": {
        "above": "USB_PORT",
        "below": "SD_INDICATOR",
        "left": null,
        "right": null
      },
      "functionalGroup": "Media/Storage",
      "shape": "circle",
      "surfaceColor": null,
      "buttonStyle": "raised",
      "labelDisplay": "above",
      "icon": null,
      "hasLed": false,
      "ledColor": null
    },
    "USB_PORT": {
      "id": "USB_PORT",
      "label": "USB port",
      "type": "port",
      "x": 35.599999999999994,
      "y": 259.9166666666667,
      "w": 51.84,
      "h": 47.06666666666667,
      "sectionId": "MEDIA",
      "labelPosition": "hidden",
      "locked": false,
      "spatialNeighbors": {
        "above": null,
        "below": "USB_STOP",
        "left": null,
        "right": "USB_INDICATOR"
      },
      "functionalGroup": "Media/Storage",
      "shape": "rectangle",
      "surfaceColor": null,
      "labelDisplay": "hidden",
      "icon": null,
      "hasLed": false,
      "ledColor": null
    },
    "USB_INDICATOR": {
      "id": "USB_INDICATOR",
      "label": "USB indicator",
      "type": "led",
      "x": 104.39999999999999,
      "y": 259.9166666666667,
      "w": 51.84,
      "h": 47.06666666666667,
      "sectionId": "MEDIA",
      "labelPosition": "hidden",
      "locked": false,
      "spatialNeighbors": {
        "above": null,
        "below": null,
        "left": "USB_PORT",
        "right": null
      },
      "functionalGroup": "Media/Storage",
      "shape": "circle",
      "surfaceColor": null,
      "labelDisplay": "hidden",
      "icon": null,
      "hasLed": true,
      "ledColor": "#22c55e",
      "ledVariant": "dot"
    },
    "TOUCH_DISPLAY": {
      "id": "TOUCH_DISPLAY",
      "label": "Touch display",
      "type": "screen",
      "x": 236,
      "y": 128.37,
      "w": 572.48,
      "h": 279.31200000000007,
      "sectionId": "DISPLAY",
      "labelPosition": "hidden",
      "locked": false,
      "spatialNeighbors": {
        "above": null,
        "below": null,
        "left": null,
        "right": null
      },
      "functionalGroup": "Display",
      "shape": "rectangle",
      "surfaceColor": null,
      "labelDisplay": "hidden",
      "icon": null,
      "hasLed": false,
      "ledColor": null
    },
    "BACK": {
      "id": "BACK",
      "label": "BACK",
      "type": "button",
      "x": 946.4000000000001,
      "y": 178.35,
      "w": 202.88000000000002,
      "h": 61.57066666666666,
      "sectionId": "SELECTOR",
      "labelPosition": "on-button",
      "locked": false,
      "spatialNeighbors": {
        "above": null,
        "below": "TAG_TRACK_REMOVE",
        "left": null,
        "right": null
      },
      "functionalGroup": "Navigation",
      "shape": "rectangle",
      "surfaceColor": null,
      "buttonStyle": "raised",
      "labelDisplay": "on-button",
      "icon": null,
      "hasLed": false,
      "ledColor": null
    },
    "TAG_TRACK_REMOVE": {
      "id": "TAG_TRACK_REMOVE",
      "label": "TAG TRACK/REMOVE",
      "type": "button",
      "x": 946.4000000000001,
      "y": 259.31333333333333,
      "w": 202.88000000000002,
      "h": 61.57066666666666,
      "sectionId": "SELECTOR",
      "labelPosition": "on-button",
      "locked": false,
      "spatialNeighbors": {
        "above": "BACK",
        "below": "ROTARY_SELECTOR",
        "left": null,
        "right": null
      },
      "functionalGroup": "Navigation",
      "shape": "rectangle",
      "surfaceColor": null,
      "buttonStyle": "raised",
      "labelDisplay": "on-button",
      "icon": null,
      "hasLed": false,
      "ledColor": null
    },
    "ROTARY_SELECTOR": {
      "id": "ROTARY_SELECTOR",
      "label": "Rotary selector",
      "type": "encoder",
      "x": 946.4000000000001,
      "y": 340.27666666666664,
      "w": 202.88000000000002,
      "h": 64,
      "sectionId": "SELECTOR",
      "labelPosition": "hidden",
      "locked": false,
      "spatialNeighbors": {
        "above": "TAG_TRACK_REMOVE",
        "below": null,
        "left": null,
        "right": null
      },
      "functionalGroup": "Navigation",
      "shape": "circle",
      "surfaceColor": null,
      "labelDisplay": "hidden",
      "icon": null,
      "hasLed": false,
      "ledColor": null
    },
    "SLIP": {
      "id": "SLIP",
      "label": "SLIP",
      "type": "button",
      "x": 9,
      "y": 376.33,
      "w": 399.36,
      "h": 28,
      "sectionId": "HOT_CUE",
      "labelPosition": "above",
      "locked": false,
      "spatialNeighbors": {
        "above": null,
        "below": "QUANTIZE",
        "left": null,
        "right": "HOT_CUE_A"
      },
      "functionalGroup": "Performance",
      "shape": "rectangle",
      "surfaceColor": null,
      "buttonStyle": "rubber",
      "labelDisplay": "above",
      "icon": null,
      "hasLed": true,
      "ledColor": "#3b82f6",
      "ledVariant": "dot"
    },
    "QUANTIZE": {
      "id": "QUANTIZE",
      "label": "QUANTIZE",
      "type": "button",
      "x": 511.2,
      "y": 375.33,
      "w": 399.36,
      "h": 28,
      "sectionId": "HOT_CUE",
      "labelPosition": "above",
      "locked": false,
      "spatialNeighbors": {
        "above": "SLIP",
        "below": "TIME_MODE_AUTO_CUE",
        "left": null,
        "right": null
      },
      "functionalGroup": "Performance",
      "shape": "rectangle",
      "surfaceColor": null,
      "buttonStyle": "rubber",
      "labelDisplay": "above",
      "icon": null,
      "hasLed": true,
      "ledColor": "#ef4444",
      "ledVariant": "dot"
    },
    "TIME_MODE_AUTO_CUE": {
      "id": "TIME_MODE_AUTO_CUE",
      "label": "TIME MODE/AUTO CUE",
      "type": "button",
      "x": 8,
      "y": 407.33,
      "w": 399.36,
      "h": 28,
      "sectionId": "HOT_CUE",
      "labelPosition": "above",
      "locked": false,
      "spatialNeighbors": {
        "above": "QUANTIZE",
        "below": null,
        "left": null,
        "right": null
      },
      "functionalGroup": "Performance",
      "shape": "circle",
      "surfaceColor": null,
      "buttonStyle": "rubber",
      "labelDisplay": "above",
      "icon": null,
      "secondaryLabel": "AUTO CUE",
      "hasLed": true,
      "ledColor": "#22c55e",
      "ledVariant": "dot"
    },
    "HOT_CUE_A": {
      "id": "HOT_CUE_A",
      "label": "HOT CUE A",
      "type": "pad",
      "x": 511.2,
      "y": 407.33,
      "w": 399.36,
      "h": 28,
      "sectionId": "HOT_CUE",
      "labelPosition": "below",
      "locked": false,
      "spatialNeighbors": {
        "above": null,
        "below": null,
        "left": "SLIP",
        "right": "HOT_CUE_B"
      },
      "functionalGroup": "Performance",
      "shape": "square",
      "surfaceColor": null,
      "buttonStyle": "rubber",
      "labelDisplay": "below",
      "icon": null,
      "hasLed": true,
      "ledColor": "#22c55e",
      "ledVariant": "dot"
    },
    "HOT_CUE_B": {
      "id": "HOT_CUE_B",
      "label": "HOT CUE B",
      "type": "pad",
      "x": 8,
      "y": 439.33,
      "w": 399.36,
      "h": 28,
      "sectionId": "HOT_CUE",
      "labelPosition": "below",
      "locked": false,
      "spatialNeighbors": {
        "above": null,
        "below": null,
        "left": "HOT_CUE_A",
        "right": "HOT_CUE_C"
      },
      "functionalGroup": "Performance",
      "shape": "square",
      "surfaceColor": null,
      "buttonStyle": "rubber",
      "labelDisplay": "below",
      "icon": null,
      "hasLed": true,
      "ledColor": "#22c55e",
      "ledVariant": "dot"
    },
    "HOT_CUE_C": {
      "id": "HOT_CUE_C",
      "label": "HOT CUE C",
      "type": "pad",
      "x": 511.2,
      "y": 439.33,
      "w": 399.36,
      "h": 28,
      "sectionId": "HOT_CUE",
      "labelPosition": "below",
      "locked": false,
      "spatialNeighbors": {
        "above": null,
        "below": null,
        "left": "HOT_CUE_B",
        "right": "HOT_CUE_D"
      },
      "functionalGroup": "Performance",
      "shape": "square",
      "surfaceColor": null,
      "buttonStyle": "rubber",
      "labelDisplay": "below",
      "icon": null,
      "hasLed": true,
      "ledColor": "#22c55e",
      "ledVariant": "dot"
    },
    "HOT_CUE_D": {
      "id": "HOT_CUE_D",
      "label": "HOT CUE D",
      "type": "pad",
      "x": 8,
      "y": 471.33,
      "w": 399.36,
      "h": 28,
      "sectionId": "HOT_CUE",
      "labelPosition": "below",
      "locked": false,
      "spatialNeighbors": {
        "above": null,
        "below": null,
        "left": "HOT_CUE_C",
        "right": "HOT_CUE_E"
      },
      "functionalGroup": "Performance",
      "shape": "square",
      "surfaceColor": null,
      "buttonStyle": "rubber",
      "labelDisplay": "below",
      "icon": null,
      "hasLed": true,
      "ledColor": "#22c55e",
      "ledVariant": "dot"
    },
    "HOT_CUE_E": {
      "id": "HOT_CUE_E",
      "label": "HOT CUE E",
      "type": "pad",
      "x": 511.2,
      "y": 471.33,
      "w": 399.36,
      "h": 28,
      "sectionId": "HOT_CUE",
      "labelPosition": "below",
      "locked": false,
      "spatialNeighbors": {
        "above": null,
        "below": null,
        "left": "HOT_CUE_D",
        "right": "HOT_CUE_F"
      },
      "functionalGroup": "Performance",
      "shape": "square",
      "surfaceColor": null,
      "buttonStyle": "rubber",
      "labelDisplay": "below",
      "icon": null,
      "hasLed": true,
      "ledColor": "#22c55e",
      "ledVariant": "dot"
    },
    "HOT_CUE_F": {
      "id": "HOT_CUE_F",
      "label": "HOT CUE F",
      "type": "pad",
      "x": 8,
      "y": 503.33,
      "w": 399.36,
      "h": 28,
      "sectionId": "HOT_CUE",
      "labelPosition": "below",
      "locked": false,
      "spatialNeighbors": {
        "above": null,
        "below": null,
        "left": "HOT_CUE_E",
        "right": "HOT_CUE_G"
      },
      "functionalGroup": "Performance",
      "shape": "square",
      "surfaceColor": null,
      "buttonStyle": "rubber",
      "labelDisplay": "below",
      "icon": null,
      "hasLed": true,
      "ledColor": "#22c55e",
      "ledVariant": "dot"
    },
    "HOT_CUE_G": {
      "id": "HOT_CUE_G",
      "label": "HOT CUE G",
      "type": "pad",
      "x": 511.2,
      "y": 503.33,
      "w": 399.36,
      "h": 28,
      "sectionId": "HOT_CUE",
      "labelPosition": "below",
      "locked": false,
      "spatialNeighbors": {
        "above": null,
        "below": null,
        "left": "HOT_CUE_F",
        "right": "HOT_CUE_H"
      },
      "functionalGroup": "Performance",
      "shape": "square",
      "surfaceColor": null,
      "buttonStyle": "rubber",
      "labelDisplay": "below",
      "icon": null,
      "hasLed": true,
      "ledColor": "#22c55e",
      "ledVariant": "dot"
    },
    "HOT_CUE_H": {
      "id": "HOT_CUE_H",
      "label": "HOT CUE H",
      "type": "pad",
      "x": 8,
      "y": 535.3299999999999,
      "w": 399.36,
      "h": 28,
      "sectionId": "HOT_CUE",
      "labelPosition": "below",
      "locked": false,
      "spatialNeighbors": {
        "above": null,
        "below": null,
        "left": "HOT_CUE_G",
        "right": null
      },
      "functionalGroup": "Performance",
      "shape": "square",
      "surfaceColor": null,
      "buttonStyle": "rubber",
      "labelDisplay": "below",
      "icon": null,
      "hasLed": true,
      "ledColor": "#22c55e",
      "ledVariant": "dot"
    },
    "TRACK_FILTER_EDIT": {
      "id": "TRACK_FILTER_EDIT",
      "label": "TRACK FILTER/EDIT",
      "type": "button",
      "x": 845.5999999999999,
      "y": 619.35,
      "w": 130.56,
      "h": 35.31333333333333,
      "sectionId": "JOG_CONTROLS",
      "labelPosition": "on-button",
      "locked": false,
      "spatialNeighbors": {
        "above": null,
        "below": "SHORTCUT",
        "left": null,
        "right": null
      },
      "functionalGroup": "Jog Settings",
      "shape": "rectangle",
      "surfaceColor": null,
      "buttonStyle": "raised",
      "labelDisplay": "on-button",
      "icon": null,
      "hasLed": false,
      "ledColor": null
    },
    "SHORTCUT": {
      "id": "SHORTCUT",
      "label": "SHORTCUT",
      "type": "button",
      "x": 1012.8,
      "y": 619.35,
      "w": 130.56,
      "h": 35.31333333333333,
      "sectionId": "JOG_CONTROLS",
      "labelPosition": "on-button",
      "locked": false,
      "spatialNeighbors": {
        "above": "TRACK_FILTER_EDIT",
        "below": "VINYL_SPEED_ADJ",
        "left": null,
        "right": null
      },
      "functionalGroup": "Jog Settings",
      "shape": "rectangle",
      "surfaceColor": null,
      "buttonStyle": "raised",
      "labelDisplay": "on-button",
      "icon": null,
      "hasLed": false,
      "ledColor": null
    },
    "VINYL_SPEED_ADJ": {
      "id": "VINYL_SPEED_ADJ",
      "label": "VINYL SPEED ADJ. TOUCH/BRAKE",
      "type": "knob",
      "x": 845.5999999999999,
      "y": 658.6633333333334,
      "w": 130.56,
      "h": 35.31333333333333,
      "sectionId": "JOG_CONTROLS",
      "labelPosition": "above",
      "locked": false,
      "spatialNeighbors": {
        "above": "SHORTCUT",
        "below": null,
        "left": null,
        "right": "JOG_MODE"
      },
      "functionalGroup": "Jog Settings",
      "shape": "circle",
      "surfaceColor": null,
      "labelDisplay": "above",
      "icon": null,
      "secondaryLabel": "TOUCH/BRAKE",
      "hasLed": false,
      "ledColor": null
    },
    "JOG_MODE": {
      "id": "JOG_MODE",
      "label": "JOG MODE",
      "type": "button",
      "x": 1012.8,
      "y": 658.6633333333334,
      "w": 130.56,
      "h": 35.31333333333333,
      "sectionId": "JOG_CONTROLS",
      "labelPosition": "above",
      "locked": false,
      "spatialNeighbors": {
        "above": null,
        "below": "VINYL_CDJ_INDICATOR",
        "left": "VINYL_SPEED_ADJ",
        "right": null
      },
      "functionalGroup": "Jog Settings",
      "shape": "rectangle",
      "surfaceColor": null,
      "buttonStyle": "raised",
      "labelDisplay": "above",
      "icon": null,
      "hasLed": false,
      "ledColor": null
    },
    "VINYL_CDJ_INDICATOR": {
      "id": "VINYL_CDJ_INDICATOR",
      "label": "VINYL/CDJ indicator",
      "type": "led",
      "x": 845.5999999999999,
      "y": 697.9766666666667,
      "w": 130.56,
      "h": 28.250666666666667,
      "sectionId": "JOG_CONTROLS",
      "labelPosition": "on-button",
      "locked": false,
      "spatialNeighbors": {
        "above": "JOG_MODE",
        "below": "JOG_ADJUST",
        "left": null,
        "right": null
      },
      "functionalGroup": "Jog Settings",
      "shape": "rectangle",
      "surfaceColor": null,
      "labelDisplay": "on-button",
      "icon": null,
      "hasLed": true,
      "ledColor": "#22c55e",
      "ledVariant": "dual-label"
    },
    "JOG_ADJUST": {
      "id": "JOG_ADJUST",
      "label": "JOG ADJUST",
      "type": "knob",
      "x": 1012.8,
      "y": 697.9766666666667,
      "w": 130.56,
      "h": 35.31333333333333,
      "sectionId": "JOG_CONTROLS",
      "labelPosition": "above",
      "locked": false,
      "spatialNeighbors": {
        "above": "VINYL_CDJ_INDICATOR",
        "below": null,
        "left": null,
        "right": null
      },
      "functionalGroup": "Jog Settings",
      "shape": "circle",
      "surfaceColor": null,
      "labelDisplay": "above",
      "icon": null,
      "hasLed": false,
      "ledColor": null
    },
    "LOOP_IN_CUE": {
      "id": "LOOP_IN_CUE",
      "label": "IN/CUE",
      "type": "button",
      "x": -1.5999999999999996,
      "y": 616.41,
      "w": 134.88,
      "h": 42.212,
      "sectionId": "LOOP",
      "labelPosition": "above",
      "locked": false,
      "spatialNeighbors": {
        "above": null,
        "below": "RELOOP_EXIT",
        "left": null,
        "right": "LOOP_OUT"
      },
      "functionalGroup": "Loop",
      "shape": "circle",
      "surfaceColor": null,
      "buttonStyle": "raised",
      "labelDisplay": "above",
      "icon": null,
      "secondaryLabel": "IN ADJUST",
      "hasLed": true,
      "ledColor": "#22c55e",
      "ledVariant": "dot"
    },
    "LOOP_OUT": {
      "id": "LOOP_OUT",
      "label": "OUT",
      "type": "button",
      "x": 171,
      "y": 616.41,
      "w": 134.88,
      "h": 42.212,
      "sectionId": "LOOP",
      "labelPosition": "above",
      "locked": false,
      "spatialNeighbors": {
        "above": null,
        "below": "EIGHT_BEAT_LOOP",
        "left": "LOOP_IN_CUE",
        "right": null
      },
      "functionalGroup": "Loop",
      "shape": "circle",
      "surfaceColor": null,
      "buttonStyle": "raised",
      "labelDisplay": "above",
      "icon": null,
      "secondaryLabel": "OUT ADJUST",
      "hasLed": true,
      "ledColor": "#22c55e",
      "ledVariant": "dot"
    },
    "RELOOP_EXIT": {
      "id": "RELOOP_EXIT",
      "label": "LOOP RELOOP/EXIT",
      "type": "button",
      "x": -1.5999999999999996,
      "y": 673.175,
      "w": 88.85333333333334,
      "h": 42.212,
      "sectionId": "LOOP",
      "labelPosition": "above",
      "locked": false,
      "spatialNeighbors": {
        "above": "LOOP_IN_CUE",
        "below": null,
        "left": null,
        "right": "FOUR_BEAT_LOOP"
      },
      "functionalGroup": "Loop",
      "shape": "circle",
      "surfaceColor": null,
      "buttonStyle": "raised",
      "labelDisplay": "above",
      "icon": null,
      "hasLed": true,
      "ledColor": "#22c55e",
      "ledVariant": "dot"
    },
    "FOUR_BEAT_LOOP": {
      "id": "FOUR_BEAT_LOOP",
      "label": "4 BEAT LOOP (1/2X)",
      "type": "button",
      "x": 113.46666666666667,
      "y": 673.175,
      "w": 88.85333333333334,
      "h": 42.212,
      "sectionId": "LOOP",
      "labelPosition": "above",
      "locked": false,
      "spatialNeighbors": {
        "above": "LOOP_IN_CUE",
        "below": null,
        "left": "RELOOP_EXIT",
        "right": "EIGHT_BEAT_LOOP"
      },
      "functionalGroup": "Loop",
      "shape": "circle",
      "surfaceColor": null,
      "buttonStyle": "raised",
      "labelDisplay": "above",
      "icon": null,
      "secondaryLabel": "1/2X",
      "hasLed": true,
      "ledColor": "#22c55e",
      "ledVariant": "dot"
    },
    "EIGHT_BEAT_LOOP": {
      "id": "EIGHT_BEAT_LOOP",
      "label": "8 BEAT LOOP (2X)",
      "type": "button",
      "x": 228.53333333333333,
      "y": 673.175,
      "w": 88.85333333333334,
      "h": 42.212,
      "sectionId": "LOOP",
      "labelPosition": "above",
      "locked": false,
      "spatialNeighbors": {
        "above": "LOOP_OUT",
        "below": null,
        "left": "FOUR_BEAT_LOOP",
        "right": null
      },
      "functionalGroup": "Loop",
      "shape": "circle",
      "surfaceColor": null,
      "buttonStyle": "raised",
      "labelDisplay": "above",
      "icon": null,
      "secondaryLabel": "2X",
      "hasLed": true,
      "ledColor": "#22c55e",
      "ledVariant": "dot"
    },
    "CUE_LOOP_CALL_BACK": {
      "id": "CUE_LOOP_CALL_BACK",
      "label": "CUE/LOOP CALL ◄",
      "type": "button",
      "x": 714.8,
      "y": 532.6200000000001,
      "w": 165.60000000000002,
      "h": 40.44800000000001,
      "sectionId": "CUE_MEMORY",
      "labelPosition": "hidden",
      "locked": false,
      "spatialNeighbors": {
        "above": null,
        "below": "DELETE",
        "left": null,
        "right": "CUE_LOOP_CALL_FWD"
      },
      "functionalGroup": "Cue/Memory",
      "shape": "circle",
      "surfaceColor": null,
      "buttonStyle": "raised",
      "labelDisplay": "icon-only",
      "icon": "arrow-left",
      "hasLed": false,
      "ledColor": null
    },
    "CUE_LOOP_CALL_FWD": {
      "id": "CUE_LOOP_CALL_FWD",
      "label": "CUE/LOOP CALL ►",
      "type": "button",
      "x": 925.8,
      "y": 532.6200000000001,
      "w": 165.60000000000002,
      "h": 40.44800000000001,
      "sectionId": "CUE_MEMORY",
      "labelPosition": "hidden",
      "locked": false,
      "spatialNeighbors": {
        "above": null,
        "below": "MEMORY",
        "left": "CUE_LOOP_CALL_BACK",
        "right": null
      },
      "functionalGroup": "Cue/Memory",
      "shape": "circle",
      "surfaceColor": null,
      "buttonStyle": "raised",
      "labelDisplay": "icon-only",
      "icon": "arrow-right",
      "hasLed": false,
      "ledColor": null
    },
    "DELETE": {
      "id": "DELETE",
      "label": "DELETE",
      "type": "button",
      "x": 714.8,
      "y": 587.1800000000001,
      "w": 165.60000000000002,
      "h": 40.44800000000001,
      "sectionId": "CUE_MEMORY",
      "labelPosition": "above",
      "locked": false,
      "spatialNeighbors": {
        "above": "CUE_LOOP_CALL_BACK",
        "below": null,
        "left": null,
        "right": "MEMORY"
      },
      "functionalGroup": "Cue/Memory",
      "shape": "circle",
      "surfaceColor": null,
      "buttonStyle": "raised",
      "labelDisplay": "above",
      "icon": null,
      "hasLed": false,
      "ledColor": null
    },
    "MEMORY": {
      "id": "MEMORY",
      "label": "MEMORY",
      "type": "button",
      "x": 925.8,
      "y": 587.1800000000001,
      "w": 165.60000000000002,
      "h": 40.44800000000001,
      "sectionId": "CUE_MEMORY",
      "labelPosition": "above",
      "locked": false,
      "spatialNeighbors": {
        "above": "CUE_LOOP_CALL_FWD",
        "below": null,
        "left": "DELETE",
        "right": null
      },
      "functionalGroup": "Cue/Memory",
      "shape": "circle",
      "surfaceColor": null,
      "buttonStyle": "raised",
      "labelDisplay": "above",
      "icon": null,
      "hasLed": false,
      "ledColor": null
    },
    "MASTER": {
      "id": "MASTER",
      "label": "MASTER",
      "type": "button",
      "x": 1046,
      "y": 716.37,
      "w": 97.28000000000003,
      "h": 28,
      "sectionId": "SYNC",
      "labelPosition": "on-button",
      "locked": false,
      "spatialNeighbors": {
        "above": null,
        "below": "KEY_SYNC",
        "left": null,
        "right": null
      },
      "functionalGroup": "Sync",
      "shape": "rectangle",
      "surfaceColor": null,
      "buttonStyle": "raised",
      "labelDisplay": "on-button",
      "icon": null,
      "hasLed": true,
      "ledColor": "#22c55e",
      "ledVariant": "dot"
    },
    "KEY_SYNC": {
      "id": "KEY_SYNC",
      "label": "KEY SYNC",
      "type": "button",
      "x": 1046,
      "y": 748.37,
      "w": 97.28000000000003,
      "h": 28,
      "sectionId": "SYNC",
      "labelPosition": "on-button",
      "locked": false,
      "spatialNeighbors": {
        "above": "MASTER",
        "below": "BEAT_SYNC_INST_DOUBLES",
        "left": null,
        "right": null
      },
      "functionalGroup": "Sync",
      "shape": "rectangle",
      "surfaceColor": "#ec4899",
      "buttonStyle": "raised",
      "labelDisplay": "on-button",
      "icon": null,
      "hasLed": true,
      "ledColor": "#ec4899",
      "ledVariant": "dot"
    },
    "BEAT_SYNC_INST_DOUBLES": {
      "id": "BEAT_SYNC_INST_DOUBLES",
      "label": "Beat Sync",
      "type": "button",
      "x": 1046,
      "y": 780.37,
      "w": 97.28000000000003,
      "h": 28,
      "sectionId": "SYNC",
      "labelPosition": "on-button",
      "locked": false,
      "spatialNeighbors": {
        "above": "KEY_SYNC",
        "below": null,
        "left": null,
        "right": null
      },
      "functionalGroup": "Sync",
      "shape": "rectangle",
      "surfaceColor": null,
      "buttonStyle": "raised",
      "labelDisplay": "on-button",
      "icon": null,
      "secondaryLabel": "",
      "hasLed": true,
      "ledColor": "#3b82f6",
      "ledVariant": "dot"
    },
    "BEAT_JUMP_BACK": {
      "id": "BEAT_JUMP_BACK",
      "label": "BEAT JUMP ◄",
      "type": "button",
      "x": 15.2,
      "y": 764.88,
      "w": 65.28,
      "h": 86.02533333333335,
      "sectionId": "TRANSPORT",
      "labelPosition": "hidden",
      "locked": false,
      "spatialNeighbors": {
        "above": null,
        "below": "DIRECTION_LEVER",
        "left": null,
        "right": "BEAT_JUMP_FWD"
      },
      "functionalGroup": "Transport",
      "shape": "rectangle",
      "surfaceColor": null,
      "buttonStyle": "raised",
      "labelDisplay": "icon-only",
      "icon": "arrow-left",
      "hasLed": false,
      "ledColor": null
    },
    "BEAT_JUMP_FWD": {
      "id": "BEAT_JUMP_FWD",
      "label": "BEAT JUMP ►",
      "type": "button",
      "x": 100.8,
      "y": 764.88,
      "w": 65.28,
      "h": 86.02533333333335,
      "sectionId": "TRANSPORT",
      "labelPosition": "hidden",
      "locked": false,
      "spatialNeighbors": {
        "above": null,
        "below": "DIRECTION_LEVER",
        "left": "BEAT_JUMP_BACK",
        "right": null
      },
      "functionalGroup": "Transport",
      "shape": "rectangle",
      "surfaceColor": null,
      "buttonStyle": "raised",
      "labelDisplay": "icon-only",
      "icon": "arrow-right",
      "hasLed": false,
      "ledColor": null
    },
    "CUE_BTN": {
      "id": "CUE_BTN",
      "label": "CUE",
      "type": "button",
      "x": 15.2,
      "y": 876.4116666666666,
      "w": 133.76,
      "h": 86.02533333333335,
      "sectionId": "TRANSPORT",
      "labelPosition": "on-button",
      "locked": false,
      "spatialNeighbors": {
        "above": "SEARCH_BACK",
        "below": "PLAY_PAUSE",
        "left": null,
        "right": null
      },
      "functionalGroup": "Transport",
      "shape": "circle",
      "surfaceColor": "#f59e0b",
      "buttonStyle": "transport",
      "labelDisplay": "on-button",
      "icon": null,
      "hasLed": true,
      "ledColor": "#f59e0b",
      "ledVariant": "dot"
    },
    "DIRECTION_LEVER": {
      "id": "DIRECTION_LEVER",
      "label": "DIRECTION FWD, REV, SLIP REV",
      "type": "lever",
      "x": 15.2,
      "y": 987.9433333333334,
      "w": 133.76,
      "h": 86.02533333333335,
      "sectionId": "TRANSPORT",
      "labelPosition": "above",
      "locked": false,
      "spatialNeighbors": {
        "above": "BEAT_JUMP_BACK",
        "below": "TRACK_SEARCH_BACK",
        "left": null,
        "right": null
      },
      "functionalGroup": "Transport",
      "shape": "rectangle",
      "surfaceColor": null,
      "labelDisplay": "above",
      "icon": null,
      "hasLed": true,
      "ledColor": "#22c55e",
      "ledVariant": "dot"
    },
    "PLAY_PAUSE": {
      "id": "PLAY_PAUSE",
      "label": "PLAY/PAUSE ►/II",
      "type": "button",
      "x": 15.2,
      "y": 1099.475,
      "w": 133.76,
      "h": 86.02533333333335,
      "sectionId": "TRANSPORT",
      "labelPosition": "hidden",
      "locked": false,
      "spatialNeighbors": {
        "above": "CUE_BTN",
        "below": null,
        "left": null,
        "right": null
      },
      "functionalGroup": "Transport",
      "shape": "circle",
      "surfaceColor": "#22c55e",
      "buttonStyle": "transport",
      "labelDisplay": "icon-only",
      "icon": "play-pause",
      "hasLed": true,
      "ledColor": "#22c55e",
      "ledVariant": "dot"
    },
    "SEARCH_BACK": {
      "id": "SEARCH_BACK",
      "label": "Search",
      "type": "button",
      "x": 15.2,
      "y": 1211.0066666666667,
      "w": 65.28,
      "h": 86.02533333333335,
      "sectionId": "TRANSPORT",
      "labelPosition": "hidden",
      "locked": false,
      "spatialNeighbors": {
        "above": "TRACK_SEARCH_BACK",
        "below": "CUE_BTN",
        "left": null,
        "right": "SEARCH_FWD"
      },
      "functionalGroup": "Transport",
      "shape": "rectangle",
      "surfaceColor": null,
      "buttonStyle": "raised",
      "labelDisplay": "icon-only",
      "icon": "rewind",
      "hasLed": false,
      "ledColor": null
    },
    "SEARCH_FWD": {
      "id": "SEARCH_FWD",
      "label": "Search",
      "type": "button",
      "x": 100.8,
      "y": 1211.0066666666667,
      "w": 65.28,
      "h": 86.02533333333335,
      "sectionId": "TRANSPORT",
      "labelPosition": "hidden",
      "locked": false,
      "spatialNeighbors": {
        "above": "TRACK_SEARCH_FWD",
        "below": "CUE_BTN",
        "left": "SEARCH_BACK",
        "right": null
      },
      "functionalGroup": "Transport",
      "shape": "rectangle",
      "surfaceColor": null,
      "buttonStyle": "raised",
      "labelDisplay": "icon-only",
      "icon": "fast-forward",
      "hasLed": false,
      "ledColor": null
    },
    "TRACK_SEARCH_BACK": {
      "id": "TRACK_SEARCH_BACK",
      "label": "Track/Search",
      "type": "button",
      "x": 15.2,
      "y": 1322.5383333333334,
      "w": 65.28,
      "h": 86.02533333333335,
      "sectionId": "TRANSPORT",
      "labelPosition": "hidden",
      "locked": false,
      "spatialNeighbors": {
        "above": "DIRECTION_LEVER",
        "below": "SEARCH_BACK",
        "left": null,
        "right": "TRACK_SEARCH_FWD"
      },
      "functionalGroup": "Transport",
      "shape": "circle",
      "surfaceColor": null,
      "buttonStyle": "raised",
      "labelDisplay": "icon-only",
      "icon": "skip-backward",
      "hasLed": false,
      "ledColor": null
    },
    "TRACK_SEARCH_FWD": {
      "id": "TRACK_SEARCH_FWD",
      "label": "Track/Search",
      "type": "button",
      "x": 100.8,
      "y": 1322.5383333333334,
      "w": 65.28,
      "h": 86.02533333333335,
      "sectionId": "TRANSPORT",
      "labelPosition": "hidden",
      "locked": false,
      "spatialNeighbors": {
        "above": "DIRECTION_LEVER",
        "below": "SEARCH_FWD",
        "left": "TRACK_SEARCH_BACK",
        "right": null
      },
      "functionalGroup": "Transport",
      "shape": "circle",
      "surfaceColor": null,
      "buttonStyle": "raised",
      "labelDisplay": "icon-only",
      "icon": "skip-forward",
      "hasLed": false,
      "ledColor": null
    },
    "JOG_DISPLAY": {
      "id": "JOG_DISPLAY",
      "label": "Jog display",
      "type": "screen",
      "x": 211.79999999999998,
      "y": 976.6840000000001,
      "w": 320.1600000000001,
      "h": 264.7248,
      "sectionId": "JOG_WHEEL",
      "labelPosition": "hidden",
      "locked": false,
      "spatialNeighbors": {
        "above": null,
        "below": null,
        "left": null,
        "right": null
      },
      "functionalGroup": "Jog Wheel",
      "shape": "circle",
      "surfaceColor": null,
      "labelDisplay": "hidden",
      "icon": null,
      "hasLed": false,
      "ledColor": null
    },
    "JOG_WHEEL": {
      "id": "JOG_WHEEL",
      "label": "Jog wheel (–REV/+FWD)",
      "type": "wheel",
      "x": 615.9999969482421,
      "y": 976.6840000000001,
      "w": 320.1600000000001,
      "h": 264.7248,
      "sectionId": "JOG_WHEEL",
      "labelPosition": "hidden",
      "locked": false,
      "spatialNeighbors": {
        "above": null,
        "below": null,
        "left": null,
        "right": null
      },
      "functionalGroup": "Jog Wheel",
      "shape": "circle",
      "surfaceColor": null,
      "labelDisplay": "hidden",
      "icon": null,
      "hasLed": true,
      "ledColor": "#22c55e",
      "ledVariant": "bar"
    },
    "TEMPO_RANGE": {
      "id": "TEMPO_RANGE",
      "label": "TEMPO ±6/±10/±16/WIDE",
      "type": "button",
      "x": 966.8000000000001,
      "y": 881.01,
      "w": 92.64,
      "h": 135.65866666666668,
      "sectionId": "TEMPO",
      "labelPosition": "above",
      "locked": false,
      "spatialNeighbors": {
        "above": null,
        "below": "MASTER_TEMPO",
        "left": null,
        "right": "TEMPO_SLIDER"
      },
      "functionalGroup": "Tempo",
      "shape": "circle",
      "surfaceColor": null,
      "buttonStyle": "raised",
      "labelDisplay": "above",
      "icon": null,
      "secondaryLabel": "±6/±10/±16/WIDE",
      "hasLed": false,
      "ledColor": null
    },
    "MASTER_TEMPO": {
      "id": "MASTER_TEMPO",
      "label": "MASTER TEMPO",
      "type": "button",
      "x": 1086.6000000000001,
      "y": 881.01,
      "w": 92.64,
      "h": 135.65866666666668,
      "sectionId": "TEMPO",
      "labelPosition": "above",
      "locked": false,
      "spatialNeighbors": {
        "above": "TEMPO_RANGE",
        "below": "TEMPO_RESET",
        "left": null,
        "right": "TEMPO_SLIDER"
      },
      "functionalGroup": "Tempo",
      "shape": "circle",
      "surfaceColor": null,
      "buttonStyle": "raised",
      "labelDisplay": "above",
      "icon": null,
      "hasLed": true,
      "ledColor": "#f59e0b",
      "ledVariant": "dot"
    },
    "TEMPO_SLIDER": {
      "id": "TEMPO_SLIDER",
      "label": "TEMPO slider",
      "type": "fader",
      "x": 966.8000000000001,
      "y": 1054.5833333333333,
      "w": 92.64,
      "h": 160,
      "sectionId": "TEMPO",
      "labelPosition": "above",
      "locked": false,
      "spatialNeighbors": {
        "above": null,
        "below": null,
        "left": "MASTER_TEMPO",
        "right": null
      },
      "functionalGroup": "Tempo",
      "shape": "rectangle",
      "surfaceColor": null,
      "labelDisplay": "above",
      "icon": null,
      "hasLed": false,
      "ledColor": null
    },
    "TEMPO_RESET": {
      "id": "TEMPO_RESET",
      "label": "TEMPO RESET",
      "type": "button",
      "x": 1086.6000000000001,
      "y": 1054.5833333333333,
      "w": 92.64,
      "h": 135.65866666666668,
      "sectionId": "TEMPO",
      "labelPosition": "above",
      "locked": false,
      "spatialNeighbors": {
        "above": "MASTER_TEMPO",
        "below": null,
        "left": null,
        "right": "TEMPO_RESET_INDICATOR"
      },
      "functionalGroup": "Tempo",
      "shape": "circle",
      "surfaceColor": null,
      "buttonStyle": "raised",
      "labelDisplay": "above",
      "icon": null,
      "hasLed": false,
      "ledColor": null
    },
    "TEMPO_RESET_INDICATOR": {
      "id": "TEMPO_RESET_INDICATOR",
      "label": "TEMPO RESET indicator",
      "type": "led",
      "x": 966.8000000000001,
      "y": 1228.1566666666668,
      "w": 92.64,
      "h": 135.65866666666668,
      "sectionId": "TEMPO",
      "labelPosition": "hidden",
      "locked": false,
      "spatialNeighbors": {
        "above": "TEMPO_SLIDER",
        "below": null,
        "left": "TEMPO_RESET",
        "right": null
      },
      "functionalGroup": "Tempo",
      "shape": "circle",
      "surfaceColor": null,
      "labelDisplay": "hidden",
      "icon": null,
      "hasLed": true,
      "ledColor": "#22c55e",
      "ledVariant": "dot"
    }
  },
  "editorLabels": [
    {
      "id": "label-USB_STOP",
      "controlId": "USB_STOP",
      "text": "USB STOP",
      "x": 36,
      "y": 179,
      "fontSize": 8,
      "align": "center"
    },
    {
      "id": "label-SLIP",
      "controlId": "SLIP",
      "text": "SLIP",
      "x": 9,
      "y": 358,
      "fontSize": 8,
      "align": "center"
    },
    {
      "id": "label-QUANTIZE",
      "controlId": "QUANTIZE",
      "text": "QUANTIZE",
      "x": 511,
      "y": 357,
      "fontSize": 8,
      "align": "center"
    },
    {
      "id": "label-TIME_MODE_AUTO_CUE",
      "controlId": "TIME_MODE_AUTO_CUE",
      "text": "TIME MODE/AUTO CUE",
      "x": 8,
      "y": 377,
      "fontSize": 8,
      "align": "center"
    },
    {
      "id": "label-HOT_CUE_A",
      "controlId": "HOT_CUE_A",
      "text": "HOT CUE A",
      "x": 511,
      "y": 441,
      "fontSize": 8,
      "align": "center"
    },
    {
      "id": "label-HOT_CUE_B",
      "controlId": "HOT_CUE_B",
      "text": "HOT CUE B",
      "x": 8,
      "y": 473,
      "fontSize": 8,
      "align": "center"
    },
    {
      "id": "label-HOT_CUE_C",
      "controlId": "HOT_CUE_C",
      "text": "HOT CUE C",
      "x": 511,
      "y": 473,
      "fontSize": 8,
      "align": "center"
    },
    {
      "id": "label-HOT_CUE_D",
      "controlId": "HOT_CUE_D",
      "text": "HOT CUE D",
      "x": 8,
      "y": 505,
      "fontSize": 8,
      "align": "center"
    },
    {
      "id": "label-HOT_CUE_E",
      "controlId": "HOT_CUE_E",
      "text": "HOT CUE E",
      "x": 511,
      "y": 505,
      "fontSize": 8,
      "align": "center"
    },
    {
      "id": "label-HOT_CUE_F",
      "controlId": "HOT_CUE_F",
      "text": "HOT CUE F",
      "x": 8,
      "y": 537,
      "fontSize": 8,
      "align": "center"
    },
    {
      "id": "label-HOT_CUE_G",
      "controlId": "HOT_CUE_G",
      "text": "HOT CUE G",
      "x": 511,
      "y": 537,
      "fontSize": 8,
      "align": "center"
    },
    {
      "id": "label-HOT_CUE_H",
      "controlId": "HOT_CUE_H",
      "text": "HOT CUE H",
      "x": 8,
      "y": 569,
      "fontSize": 8,
      "align": "center"
    },
    {
      "id": "label-VINYL_SPEED_ADJ",
      "controlId": "VINYL_SPEED_ADJ",
      "text": "VINYL SPEED ADJ. TOUCH/BRAKE",
      "x": 846,
      "y": 629,
      "fontSize": 8,
      "align": "center"
    },
    {
      "id": "label-JOG_MODE",
      "controlId": "JOG_MODE",
      "text": "JOG MODE",
      "x": 1013,
      "y": 641,
      "fontSize": 8,
      "align": "center"
    },
    {
      "id": "label-JOG_ADJUST",
      "controlId": "JOG_ADJUST",
      "text": "JOG ADJUST",
      "x": 1013,
      "y": 680,
      "fontSize": 8,
      "align": "center"
    },
    {
      "id": "label-LOOP_IN_CUE",
      "controlId": "LOOP_IN_CUE",
      "text": "IN/CUE",
      "x": -2,
      "y": 586,
      "fontSize": 8,
      "align": "center"
    },
    {
      "id": "label-LOOP_OUT",
      "controlId": "LOOP_OUT",
      "text": "OUT",
      "x": 171,
      "y": 586,
      "fontSize": 8,
      "align": "center"
    },
    {
      "id": "label-RELOOP_EXIT",
      "controlId": "RELOOP_EXIT",
      "text": "LOOP RELOOP/EXIT",
      "x": -2,
      "y": 655,
      "fontSize": 8,
      "align": "center"
    },
    {
      "id": "label-FOUR_BEAT_LOOP",
      "controlId": "FOUR_BEAT_LOOP",
      "text": "4 BEAT LOOP (1/2X)",
      "x": 113,
      "y": 643,
      "fontSize": 8,
      "align": "center"
    },
    {
      "id": "label-EIGHT_BEAT_LOOP",
      "controlId": "EIGHT_BEAT_LOOP",
      "text": "8 BEAT LOOP (2X)",
      "x": 229,
      "y": 643,
      "fontSize": 8,
      "align": "center"
    },
    {
      "id": "label-DELETE",
      "controlId": "DELETE",
      "text": "DELETE",
      "x": 715,
      "y": 569,
      "fontSize": 8,
      "align": "center"
    },
    {
      "id": "label-MEMORY",
      "controlId": "MEMORY",
      "text": "MEMORY",
      "x": 926,
      "y": 569,
      "fontSize": 8,
      "align": "center"
    },
    {
      "id": "label-DIRECTION_LEVER",
      "controlId": "DIRECTION_LEVER",
      "text": "DIRECTION FWD, REV, SLIP REV",
      "x": 15,
      "y": 970,
      "fontSize": 8,
      "align": "center"
    },
    {
      "id": "label-TEMPO_RANGE",
      "controlId": "TEMPO_RANGE",
      "text": "TEMPO ±6/±10/±16/WIDE",
      "x": 967,
      "y": 851,
      "fontSize": 8,
      "align": "center"
    },
    {
      "id": "label-MASTER_TEMPO",
      "controlId": "MASTER_TEMPO",
      "text": "MASTER TEMPO",
      "x": 1087,
      "y": 863,
      "fontSize": 8,
      "align": "center"
    },
    {
      "id": "label-TEMPO_SLIDER",
      "controlId": "TEMPO_SLIDER",
      "text": "TEMPO slider",
      "x": 967,
      "y": 1037,
      "fontSize": 8,
      "align": "center"
    },
    {
      "id": "label-TEMPO_RESET",
      "controlId": "TEMPO_RESET",
      "text": "TEMPO RESET",
      "x": 1087,
      "y": 1037,
      "fontSize": 8,
      "align": "center"
    }
  ],
  "controlGroups": [
    {
      "id": "group-1775323481200-d6g3wz",
      "name": "Group 2",
      "controlIds": [
        "JOG_WHEEL",
        "JOG_DISPLAY",
        "SLIP",
        "QUANTIZE"
      ]
    },
    {
      "id": "group-1775323483120-33ez6i",
      "name": "Group 2",
      "controlIds": [
        "TIME_MODE_AUTO_CUE",
        "HOT_CUE_A",
        "HOT_CUE_B",
        "HOT_CUE_C"
      ]
    }
  ],
  "canvasWidth": 1200,
  "canvasHeight": 1470,
  "_manifestVersion": "d312ff26",
  "controlScale": 1,
  "zoom": 1,
  "cleanupGap": 8,
  "panelScale": 1,
  "keyboard": null
}